process/Load.py
process/__init__.py
process/fields.py
process/util.py
updatehnk-0.1.1.dist-info/LICENSE.txt
updatehnk-0.1.1.dist-info/METADATA
updatehnk-0.1.1.dist-info/WHEEL
updatehnk-0.1.1.dist-info/top_level.txt
updatehnk-0.1.1.dist-info/RECORD
