Metadata-Version: 2.1
Name: updatehnk
Version: 0.1.1
Summary: Update coolers info
Author: Eduardo Martinez
Author-email: eduardo.martinez.2117@gmail.com
License: MIT
Keywords: heineken,python,bigquery,storage,bucket
License-File: LICENSE.txt
Requires-Dist: google-cloud-storage
Requires-Dist: google-cloud-bigquery
Requires-Dist: pytz
